h2o_mlflow_flavor/__init__.py
h2o_mlflow_flavor-0.1.0.dist-info/METADATA
h2o_mlflow_flavor-0.1.0.dist-info/WHEEL
h2o_mlflow_flavor-0.1.0.dist-info/top_level.txt
h2o_mlflow_flavor-0.1.0.dist-info/RECORD
