Metadata-Version: 2.1
Name: h2o-mlflow-flavor
Version: 0.1.0
Summary: A mlflow flavor for working with H2O-3 MOJO and POJO models
Home-page: https://github.com/h2oai/h2o-3.git
Author: H2O.ai
Author-email: support@h2o.ai
License: Apache v2
Keywords: ML Flow,H2O-3
Classifier: Development Status :: 3 - Alpha
Classifier: Intended Audience :: Education
Classifier: Intended Audience :: Developers
Classifier: Intended Audience :: Science/Research
Classifier: Intended Audience :: Customer Service
Classifier: Intended Audience :: Financial and Insurance Industry
Classifier: Intended Audience :: Healthcare Industry
Classifier: Intended Audience :: Telecommunications Industry
Classifier: Topic :: Scientific/Engineering :: Artificial Intelligence
Classifier: Topic :: Scientific/Engineering :: Information Analysis
Classifier: License :: OSI Approved :: Apache Software License
Classifier: Programming Language :: Python :: 3.8
Classifier: Programming Language :: Python :: 3.9
Classifier: Programming Language :: Python :: 3.10
Classifier: Programming Language :: Python :: 3.11
Requires-Dist: mlflow (>=1.29.0)
